{"files":{"apps/cms/dist/assets/index-UoMatvTy.js":{"size":207804,"mtime_nanos":1781529157188260000,"mode":420,"is_dir":false},"apps/cms/dist/assets/index-Cxs9jHWy.css":{"size":1156,"mtime_nanos":1781529157188260000,"mode":420,"is_dir":false},"apps/cms/dist":{"size":0,"mtime_nanos":0,"mode":0,"is_dir":true},"apps/cms/dist/assets":{"size":0,"mtime_nanos":0,"mode":0,"is_dir":true},"apps/cms/.turbo/turbo-build.log":{"size":736,"mtime_nanos":1781529157566598500,"mode":420,"is_dir":false},"apps/cms/dist/index.html":{"size":808,"mtime_nanos":1781529157194269600,"mode":420,"is_dir":false}},"order":["apps/cms/.turbo/turbo-build.log","apps/cms/dist","apps/cms/dist/assets","apps/cms/dist/assets/index-Cxs9jHWy.css","apps/cms/dist/assets/index-UoMatvTy.js","apps/cms/dist/index.html"]}