{"files":{"packages\\utils\\dist\\index.d.ts.map":{"size":363,"mtime_nanos":1781513158953379200,"mode":420,"is_dir":false},"packages\\utils\\.turbo\\turbo-build.log":{"size":100,"mtime_nanos":1781513158951369700,"mode":420,"is_dir":false},"packages\\utils\\dist\\index.d.ts":{"size":320,"mtime_nanos":1781513158951369700,"mode":420,"is_dir":false},"packages\\utils\\dist\\index.js":{"size":770,"mtime_nanos":1781513158953379200,"mode":420,"is_dir":false}},"order":["packages\\utils\\.turbo\\turbo-build.log","packages\\utils\\dist\\index.d.ts","packages\\utils\\dist\\index.d.ts.map","packages\\utils\\dist\\index.js"]}